{
  "tag": "2023-10-18_230712",
  "event": {
    "event_type": "touch",
    "log_lines": null,
    "x": null,
    "y": null,
    "view": {
      "package": "org.mozilla.firefox",
      "visible": true,
      "checkable": false,
      "child_count": 0,
      "editable": false,
      "clickable": true,
      "is_password": false,
      "focusable": true,
      "enabled": true,
      "content_description": null,
      "children": [],
      "focused": false,
      "bounds": [
        [
          457,
          581
        ],
        [
          996,
          689
        ]
      ],
      "resource_id": "org.mozilla.firefox:id/cfr_pos_button",
      "checked": false,
      "text": "Add shortcut",
      "class": "android.widget.Button",
      "scrollable": false,
      "selected": false,
      "long_clickable": false,
      "parent": 3,
      "temp_id": 5,
      "size": "539*108",
      "signature": "[class]android.widget.Button[resource_id]org.mozilla.firefox:id/cfr_pos_button[text]Add shortcut[enabled,,]",
      "view_str": "35353d1665e76e5fb7d86b6b7c03278e",
      "content_free_signature": "[class]android.widget.Button[resource_id]org.mozilla.firefox:id/cfr_pos_button"
    }
  },
  "start_state": "a092b2d1a8d39a95e6009597941c2860",
  "stop_state": "22b34f20b9a5b6ee36d9bd92f96d5913",
  "event_str": "TouchEvent(state=a092b2d1a8d39a95e6009597941c2860, view=35353d1665e76e5fb7d86b6b7c03278e(HomeActivity/Button-Add shortc))"
}