{
  "tag": "2023-10-19_060429",
  "event": {
    "event_type": "touch",
    "log_lines": null,
    "x": null,
    "y": null,
    "view": {
      "package": "com.brosmike.airpushdetector",
      "visible": true,
      "checkable": false,
      "child_count": 0,
      "editable": false,
      "clickable": true,
      "is_password": false,
      "focusable": true,
      "enabled": true,
      "content_description": null,
      "children": [],
      "focused": false,
      "bounds": [
        [
          582,
          1150
        ],
        [
          969,
          1294
        ]
      ],
      "resource_id": "android:id/button2",
      "checked": false,
      "text": "IT DIDN'T WORK!",
      "class": "android.widget.Button",
      "scrollable": false,
      "selected": false,
      "long_clickable": false,
      "parent": 13,
      "temp_id": 15,
      "size": "387*144",
      "signature": "[class]android.widget.Button[resource_id]android:id/button2[text]IT DIDN'T WORK![enabled,,]",
      "view_str": "ef94211511fe84635f30161f0c03a12b",
      "content_free_signature": "[class]android.widget.Button[resource_id]android:id/button2"
    }
  },
  "start_state": "73b3abc155a72ab8bc3418ceedbbadac",
  "stop_state": "da98cbc11a47d5b1ba6324641068f1db",
  "event_str": "TouchEvent(state=73b3abc155a72ab8bc3418ceedbbadac, view=ef94211511fe84635f30161f0c03a12b(DetectorActivity/Button-IT DIDN'T ))"
}