{
  "tag": "2023-10-19_004724",
  "event": {
    "event_type": "touch",
    "log_lines": null,
    "x": null,
    "y": null,
    "view": {
      "package": "com.uberspot.a2048",
      "visible": true,
      "checkable": false,
      "child_count": 0,
      "editable": false,
      "clickable": false,
      "is_password": false,
      "focusable": false,
      "enabled": true,
      "content_description": null,
      "children": [],
      "focused": false,
      "bounds": [
        [
          555,
          714
        ],
        [
          729,
          891
        ]
      ],
      "resource_id": null,
      "checked": false,
      "text": "4",
      "class": "android.view.View",
      "scrollable": false,
      "selected": false,
      "long_clickable": false,
      "parent": 32,
      "temp_id": 33,
      "size": "174*177",
      "signature": "[class]android.view.View[resource_id]None[text]4[enabled,,]",
      "view_str": "f49ebf57ed4b9259becde5eb7afb0c54",
      "content_free_signature": "[class]android.view.View[resource_id]None"
    }
  },
  "start_state": "1895e9c0de2ac4d5f965892c16060580",
  "stop_state": "1895e9c0de2ac4d5f965892c16060580",
  "event_str": "TouchEvent(state=1895e9c0de2ac4d5f965892c16060580, view=f49ebf57ed4b9259becde5eb7afb0c54(MainActivity/View-4))"
}