{
  "tag": "2023-10-19_074552",
  "event": {
    "event_type": "touch",
    "log_lines": null,
    "x": null,
    "y": null,
    "view": {
      "package": "org.mozilla.firefox",
      "visible": true,
      "checkable": false,
      "child_count": 1,
      "editable": false,
      "clickable": true,
      "is_password": false,
      "focusable": true,
      "enabled": true,
      "content_description": "Mozilla Support Logo",
      "children": [
        15
      ],
      "focused": false,
      "bounds": [
        [
          48,
          108
        ],
        [
          336,
          231
        ]
      ],
      "resource_id": null,
      "checked": false,
      "text": null,
      "class": "android.view.View",
      "scrollable": false,
      "selected": false,
      "long_clickable": false,
      "parent": 13,
      "temp_id": 14,
      "size": "288*123",
      "signature": "[class]android.view.View[resource_id]None[text]None[enabled,,]",
      "view_str": "1870aaa71534a8b70cf743ead3e84d20",
      "content_free_signature": "[class]android.view.View[resource_id]None"
    }
  },
  "start_state": "f017279ebb89a29ac61ff9364c3ee1f2",
  "stop_state": "c08616ec1f80d93769fd1684bf1b2983",
  "event_str": "TouchEvent(state=f017279ebb89a29ac61ff9364c3ee1f2, view=1870aaa71534a8b70cf743ead3e84d20(HomeActivity/View-))"
}