{
  "tag": "2023-10-19_074203",
  "event": {
    "event_type": "touch",
    "log_lines": null,
    "x": null,
    "y": null,
    "view": {
      "package": "org.mozilla.firefox",
      "visible": true,
      "checkable": false,
      "child_count": 1,
      "editable": false,
      "clickable": true,
      "is_password": false,
      "focusable": true,
      "enabled": true,
      "content_description": null,
      "children": [
        34
      ],
      "focused": false,
      "bounds": [
        [
          960,
          119
        ],
        [
          1032,
          191
        ]
      ],
      "resource_id": null,
      "checked": false,
      "text": "Account Panel",
      "class": "android.widget.Button",
      "scrollable": false,
      "selected": false,
      "long_clickable": false,
      "parent": 32,
      "temp_id": 33,
      "size": "72*72",
      "signature": "[class]android.widget.Button[resource_id]None[text]Account Panel[enabled,,]",
      "view_str": "fe0f8a7b57f9ec0992e2c96ff0d756dd",
      "content_free_signature": "[class]android.widget.Button[resource_id]None"
    }
  },
  "start_state": "ae4de81c3cdaf9845e841db0d041c30b",
  "stop_state": "54f5e6b11ae5c99dade48a5cf53edfa1",
  "event_str": "TouchEvent(state=ae4de81c3cdaf9845e841db0d041c30b, view=fe0f8a7b57f9ec0992e2c96ff0d756dd(HomeActivity/Button-Account Pa))"
}