{
  "tag": "2023-10-19_074259",
  "event": {
    "event_type": "touch",
    "log_lines": null,
    "x": null,
    "y": null,
    "view": {
      "package": "org.mozilla.firefox",
      "visible": true,
      "checkable": false,
      "child_count": 0,
      "editable": false,
      "clickable": true,
      "is_password": false,
      "focusable": false,
      "enabled": true,
      "content_description": "Accept and edit suggestion",
      "children": [],
      "focused": false,
      "bounds": [
        [
          984,
          288
        ],
        [
          1056,
          360
        ]
      ],
      "resource_id": null,
      "checked": false,
      "text": null,
      "class": "android.widget.ImageView",
      "scrollable": false,
      "selected": false,
      "long_clickable": false,
      "parent": 10,
      "temp_id": 13,
      "size": "72*72",
      "signature": "[class]android.widget.ImageView[resource_id]None[text]None[enabled,,]",
      "view_str": "2087d74a6d919e42a3b1e227015066ff",
      "content_free_signature": "[class]android.widget.ImageView[resource_id]None"
    }
  },
  "start_state": "e4e3058e8d28aa62595ee867a471bfb9",
  "stop_state": "bed735167ef795551cf5c24acb43df3e",
  "event_str": "TouchEvent(state=e4e3058e8d28aa62595ee867a471bfb9, view=2087d74a6d919e42a3b1e227015066ff(HomeActivity/ImageView-))"
}