{
  "tag": "2023-10-19_142718",
  "event": {
    "event_type": "touch",
    "log_lines": null,
    "x": null,
    "y": null,
    "view": {
      "package": "org.ligi.ajsha",
      "visible": true,
      "checkable": false,
      "child_count": 0,
      "editable": false,
      "clickable": true,
      "is_password": false,
      "focusable": false,
      "enabled": true,
      "content_description": null,
      "children": [],
      "focused": false,
      "bounds": [
        [
          75,
          1523
        ],
        [
          1005,
          1667
        ]
      ],
      "resource_id": "android:id/text1",
      "checked": false,
      "text": "views",
      "class": "android.widget.TextView",
      "scrollable": false,
      "selected": false,
      "long_clickable": false,
      "parent": 9,
      "temp_id": 18,
      "size": "930*144",
      "signature": "[class]android.widget.TextView[resource_id]android:id/text1[text]views[enabled,,]",
      "view_str": "2d91e58189edfc6b2ed4788767f9ae49",
      "content_free_signature": "[class]android.widget.TextView[resource_id]android:id/text1"
    }
  },
  "start_state": "57e6baa2a40a824c767d3168ed63fbc3",
  "stop_state": "c9431a09585c33d4400844789da31a8d",
  "event_str": "TouchEvent(state=57e6baa2a40a824c767d3168ed63fbc3, view=2d91e58189edfc6b2ed4788767f9ae49(EditActivity/TextView-views))"
}