{
  "tag": "2023-10-24_174502",
  "event": {
    "event_type": "touch",
    "log_lines": null,
    "x": null,
    "y": null,
    "view": {
      "package": "com.sina.weibo",
      "visible": true,
      "checkable": false,
      "child_count": 0,
      "editable": false,
      "clickable": true,
      "is_password": false,
      "focusable": true,
      "enabled": true,
      "content_description": null,
      "children": [],
      "focused": false,
      "bounds": [
        [
          135,
          1176
        ],
        [
          539,
          1308
        ]
      ],
      "resource_id": null,
      "checked": false,
      "text": "Disagree and Quit",
      "class": "android.widget.TextView",
      "scrollable": false,
      "selected": false,
      "long_clickable": false,
      "parent": 15,
      "temp_id": 16,
      "size": "404*132",
      "signature": "[class]android.widget.TextView[resource_id]None[text]Disagree and Quit[enabled,,]",
      "view_str": "d7a9f3eed6e707ce7d1a1547c1ea1c1f",
      "content_free_signature": "[class]android.widget.TextView[resource_id]None"
    }
  },
  "start_state": "567e946d179f673918ef1a819927883e",
  "stop_state": "5f6d51b4d0e4a8b9f79caa670d861f15",
  "event_str": "TouchEvent(state=567e946d179f673918ef1a819927883e, view=d7a9f3eed6e707ce7d1a1547c1ea1c1f(SplashActivity/TextView-Disagree a))"
}